Metadata-Version: 2.1
Name: redistensor
Version: 0.0.6
Summary: using redis to store tensor data
Home-page: 
Author: hayang
Author-email: 469358331@qq.com
Classifier: Programming Language :: Python :: 3
Classifier: License :: OSI Approved :: MIT License
Classifier: Operating System :: OS Independent
Requires-Python: >=3.6
